ezception.py
ezception-0.0.2.dist-info/LICENSE
ezception-0.0.2.dist-info/METADATA
ezception-0.0.2.dist-info/WHEEL
ezception-0.0.2.dist-info/top_level.txt
ezception-0.0.2.dist-info/RECORD
