Metadata-Version: 2.1
Name: ezception
Version: 0.0.2
Summary: Simple exceptions and messaging
Home-page: https://github.com/hrharkins/ezception
Author: Rich Harkins
Author-email: rich.harkins@gmail.com
License: UNKNOWN
Platform: UNKNOWN
Classifier: Programming Language :: Python :: 3
Classifier: License :: OSI Approved :: GNU General Public License v3 or later (GPLv3+)
Classifier: Operating System :: OS Independent
Classifier: Development Status :: 2 - Pre-Alpha
Requires-Python: >=3.6
